{
  "More":
  [
    {
      "id":1,
      "title":"AhmadDroid",
      "image":"https://ridwanlampung1.github.io/ahmaddroid/ahicon.png",
      "link":"https://play.google.com/store/apps/dev?id=5705638003703494443"
    },
    {
      "id":2,
      "title":"Truck Simulator AMD",
      "image":"https://play-lh.googleusercontent.com/ngRUu-KrRNFNLIn_0oI2OF_h15PFEhvcctRwVhscMoFIPv-_rEZMNNXYvy9JnXX69A1enX__K5otNjcr1sx_plY=w240-h480-rw",
      "link":"https://play.google.com/store/apps/details?id=com.ahmaddroid.trucksimulatoramd"
    }
  ]

}